LICENSE
MANIFEST.in
README.rst
setup.cfg
setup.py
cgiFileUpload.egg-info/PKG-INFO
cgiFileUpload.egg-info/SOURCES.txt
cgiFileUpload.egg-info/dependency_links.txt
cgiFileUpload.egg-info/entry_points.txt
cgiFileUpload.egg-info/not-zip-safe
cgiFileUpload.egg-info/requires.txt
cgiFileUpload.egg-info/top_level.txt
cgifileupload/__init__.py
cgifileupload/image_reduce.py
cgifileupload/thumbnailer.py
cgifileupload/upload.py