Metadata-Version: 1.1
Name: cgiFileUpload
Version: 0.1.5dev
Summary: file import via CGI
Home-page: https://bitbucket.org/RobertSudwarts/cgi_file_upload/
Author: Robert Sudwarts
Author-email: robert.sudwarts@gmail.com
License: MIT
Platform: UNKNOWN
Classifier: Programming Language :: Python
Classifier: License :: OSI Approved :: MIT License
Classifier: Intended Audience :: Developers
Classifier: Development Status :: 2 - Pre-Alpha
Classifier: Topic :: Internet :: WWW/HTTP :: Dynamic Content :: CGI Tools/Libraries
Classifier: Topic :: Utilities
